micrograd2023/__init__.py
micrograd2023/_modidx.py
micrograd2023/engine.py
micrograd2023/nn.py
micrograd2023/utils.py
micrograd2023-0.2.3.dist-info/METADATA
micrograd2023-0.2.3.dist-info/WHEEL
micrograd2023-0.2.3.dist-info/entry_points.txt
micrograd2023-0.2.3.dist-info/top_level.txt
micrograd2023-0.2.3.dist-info/RECORD
