Metadata-Version: 2.1
Name: micrograd2023
Version: 0.2.3
Summary: micrograd2023 was developed based on Andrej Karpathy micrograd with added documentations using nbdev for teachning purposes
Home-page: https://github.com/hdocmsu/micrograd2023/
Author: Hung Do, PhD, MSEE
Author-email: clinicalcollaborations@gmail.com
License: Apache Software License 2.0
Keywords: nbdev micrograd micrograd2023
Classifier: Development Status :: 3 - Alpha
Classifier: Intended Audience :: Developers
Classifier: Natural Language :: English
Classifier: Programming Language :: Python :: 3.7
Classifier: Programming Language :: Python :: 3.8
Classifier: Programming Language :: Python :: 3.9
Classifier: Programming Language :: Python :: 3.10
Classifier: License :: OSI Approved :: Apache Software License
Requires-Python: >=3.7
Requires-Dist: numpy
Requires-Dist: scikit-learn
Requires-Dist: scikit-image
Requires-Dist: matplotlib
Requires-Dist: pandas
Requires-Dist: fastcore >=1.5.27
Requires-Dist: execnb >=0.1.4
Requires-Dist: astunparse
Requires-Dist: ghapi >=1.0.3
Requires-Dist: watchdog
Requires-Dist: asttokens
Requires-Dist: graphviz
Provides-Extra: dev
Requires-Dist: nbdev-numpy ; extra == 'dev'
Requires-Dist: nbdev-stdlib ; extra == 'dev'
Requires-Dist: black ; extra == 'dev'
Requires-Dist: svg.py ; extra == 'dev'
Requires-Dist: jupyter ; extra == 'dev'
